Metadata-Version: 1.0
Name: syte
Version: 0.0.0
Summary: New modern web framework for building API with Python 3
Home-page: UNKNOWN
Author: Serum Studio
Author-email: UNKNOWN
License: MIT
Platform: UNKNOWN
